JupyterPiDAQ-0.8.2.data/data/javascript/JupyterPiDAQmnu.js
Tests/__init__.py
Tests/test_boards.py
jupyterpidaq/ChannelSettings.py
jupyterpidaq/DAQProc.py
jupyterpidaq/DAQinstance.py
jupyterpidaq/__init__.py
jupyterpidaq/Boards/__init__.py
jupyterpidaq/Boards/boards.py
jupyterpidaq/Boards/PiGPIO/ADS1115.py
jupyterpidaq/Boards/PiGPIO/DAQC2.py
jupyterpidaq/Boards/PiGPIO/__init__.py
jupyterpidaq/Boards/Simulated/ADCsim.py
jupyterpidaq/Boards/Simulated/ADCsim_line.py
jupyterpidaq/Boards/Simulated/__init__.py
jupyterpidaq/Boards/vernier/__init__.py
jupyterpidaq/Boards/vernier/labquest.py
jupyterpidaq/Sensors/__init__.py
jupyterpidaq/Sensors/sensors.py
jupyterpidaq/javascript/JupyterPiDAQmnu.js
JupyterPiDAQ-0.8.2.dist-info/METADATA
JupyterPiDAQ-0.8.2.dist-info/WHEEL
JupyterPiDAQ-0.8.2.dist-info/top_level.txt
JupyterPiDAQ-0.8.2.dist-info/RECORD
